{
  "title": "lucid-origin",
  "content": "Text-to-Image • Leonardo\n\n@cf/leonardo/lucid-origin\n\nLucid Origin from Leonardo.AI is their most adaptable and prompt-responsive model to date. Whether you're generating images with sharp graphic design, stunning full-HD renders, or highly specific creative direction, it adheres closely to your prompts, renders text with accuracy, and supports a wide array of visual styles and aesthetics – from stylized concept art to crisp product mockups.\n\n| Model Info | |\n| - | - |\n| Terms and License | [link](https://leonardo.ai/terms-of-service/) |\n| Partner | Yes |\n| Unit Pricing | $0.007 per 512 by 512 tile, $0.00013 per step |\n\n\\* indicates a required field\n\n* `prompt` string required min 1\n\nA text description of the image you want to generate.\n\n* `guidance` number default 4.5 min 0 max 10\n\nControls how closely the generated image should adhere to the prompt; higher values make the image more aligned with the prompt\n\n* `seed` integer min 0\n\nRandom seed for reproducibility of the image generation\n\n* `height` integer default 1120 min 0 max 2500\n\nThe height of the generated image in pixels\n\n* `width` integer default 1120 min 0 max 2500\n\nThe width of the generated image in pixels\n\n* `num_steps` integer min 1 max 40\n\nThe number of diffusion steps; higher values can improve quality but take longer\n\n* `steps` integer min 1 max 40\n\nThe number of diffusion steps; higher values can improve quality but take longer\n\nThe generated image in Base64 format.\n\nThe following schemas are based on JSON Schema\n\n<page>\n---\ntitle: m2m100-1.2b · Cloudflare Workers AI docs\ndescription: Multilingual encoder-decoder (seq-to-seq) model trained for\n  Many-to-Many multilingual translation\nchatbotDeprioritize: false\nsource_url:\n  html: https://developers.cloudflare.com/workers-ai/models/m2m100-1.2b/\n  md: https://developers.cloudflare.com/workers-ai/models/m2m100-1.2b/index.md\n---\n\n![Meta logo](https://developers.cloudflare.com/_astro/meta.x5nlFKBG.svg)",
  "code_samples": [
    {
      "code": "export interface Env {\n  AI: Ai;\n}\n\n\nexport default {\n  async fetch(request, env): Promise<Response> {\n\n\n    const inputs = {\n      prompt: \"cyberpunk cat\",\n    };\n\n\n    const response = await env.AI.run(\n      \"@cf/leonardo/lucid-origin\",\n      inputs\n    );\n\n\n    return new Response(response, {\n      headers: {\n        \"content-type\": \"image/jpg\",\n      },\n    });\n  },\n} satisfies ExportedHandler<Env>;",
      "language": "ts"
    },
    {
      "code": "curl https://api.cloudflare.com/client/v4/accounts/$CLOUDFLARE_ACCOUNT_ID/ai/run/@cf/leonardo/lucid-origin  \\\n  -X POST  \\\n  -H \"Authorization: Bearer $CLOUDFLARE_API_TOKEN\"  \\\n  -d '{ \"prompt\": \"cyberpunk cat\" }'",
      "language": "sh"
    },
    {
      "code": "{\n      \"type\": \"object\",\n      \"properties\": {\n          \"prompt\": {\n              \"type\": \"string\",\n              \"minLength\": 1,\n              \"description\": \"A text description of the image you want to generate.\"\n          },\n          \"guidance\": {\n              \"type\": \"number\",\n              \"default\": 4.5,\n              \"minimum\": 0,\n              \"maximum\": 10,\n              \"description\": \"Controls how closely the generated image should adhere to the prompt; higher values make the image more aligned with the prompt\"\n          },\n          \"seed\": {\n              \"type\": \"integer\",\n              \"minimum\": 0,\n              \"description\": \"Random seed for reproducibility of the image generation\"\n          },\n          \"height\": {\n              \"type\": \"integer\",\n              \"minimum\": 0,\n              \"maximum\": 2500,\n              \"default\": 1120,\n              \"description\": \"The height of the generated image in pixels\"\n          },\n          \"width\": {\n              \"type\": \"integer\",\n              \"minimum\": 0,\n              \"maximum\": 2500,\n              \"default\": 1120,\n              \"description\": \"The width of the generated image in pixels\"\n          },\n          \"num_steps\": {\n              \"type\": \"integer\",\n              \"minimum\": 1,\n              \"maximum\": 40,\n              \"description\": \"The number of diffusion steps; higher values can improve quality but take longer\"\n          },\n          \"steps\": {\n              \"type\": \"integer\",\n              \"minimum\": 1,\n              \"maximum\": 40,\n              \"description\": \"The number of diffusion steps; higher values can improve quality but take longer\"\n          }\n      },\n      \"required\": [\n          \"prompt\"\n      ]\n  }",
      "language": "json"
    },
    {
      "code": "{\n      \"type\": \"object\",\n      \"contentType\": \"application/json\",\n      \"properties\": {\n          \"image\": {\n              \"type\": \"string\",\n              \"description\": \"The generated image in Base64 format.\"\n          }\n      }\n  }",
      "language": "json"
    }
  ],
  "headings": [
    {
      "level": "h2",
      "text": "Usage",
      "id": "usage"
    },
    {
      "level": "h2",
      "text": "Parameters",
      "id": "parameters"
    },
    {
      "level": "h3",
      "text": "Input",
      "id": "input"
    },
    {
      "level": "h3",
      "text": "Output",
      "id": "output"
    },
    {
      "level": "h2",
      "text": "API Schemas",
      "id": "api-schemas"
    }
  ],
  "url": "llms-txt#lucid-origin",
  "links": []
}