{
  "title": "gemma-sea-lion-v4-27b-it",
  "content": "Text Generation • aisingapore\n\n@cf/aisingapore/gemma-sea-lion-v4-27b-it\n\nSEA-LION stands for Southeast Asian Languages In One Network, which is a collection of Large Language Models (LLMs) which have been pretrained and instruct-tuned for the Southeast Asia (SEA) region.\n\n| Model Info | |\n| - | - |\n| Context Window[](https://developers.cloudflare.com/workers-ai/glossary/) | 128,000 tokens |\n| Unit Pricing | $0.35 per M input tokens, $0.56 per M output tokens |\n\nTry out this model with Workers AI LLM Playground. It does not require any setup or authentication and an instant way to preview and test a model directly in the browser.\n\n[Launch the LLM Playground](https://playground.ai.cloudflare.com/?model=@cf/aisingapore/gemma-sea-lion-v4-27b-it)\n\nOpenAI compatible endpoints\n\nWorkers AI also supports OpenAI compatible API endpoints for `/v1/chat/completions` and `/v1/embeddings`. For more details, refer to [Configurations ](https://developers.cloudflare.com/workers-ai/configuration/open-ai-compatibility/).\n\n\\* indicates a required field\n\n* `prompt` string required min 1\n\nThe input text prompt for the model to generate a response.\n\nName of the LoRA (Low-Rank Adaptation) model to fine-tune the base model.\n\n* `response_format` object\n\nIf true, a chat template is not applied and you must adhere to the specific model's expected formatting.\n\nIf true, the response will be streamed back incrementally using SSE, Server Sent Events.\n\n* `max_tokens` integer default 2000\n\nThe maximum number of tokens to generate in the response.\n\n* `temperature` number default 0.6 min 0 max 5\n\nControls the randomness of the output; higher values produce more random results.\n\n* `top_p` number min 0.001 max 1\n\nAdjusts the creativity of the AI's responses by controlling how many possible words it considers. Lower values make outputs more predictable; higher values allow for more varied and creative responses.\n\n* `top_k` integer min 1 max 50\n\nLimits the AI to choose from the top 'k' most probable words. Lower values make responses more focused; higher values introduce more variety and potential surprises.\n\n* `seed` integer min 1 max 9999999999\n\nRandom seed for reproducibility of the generation.\n\n* `repetition_penalty` number min 0 max 2\n\nPenalty for repeated tokens; higher values discourage repetition.\n\n* `frequency_penalty` number min -2 max 2\n\nDecreases the likelihood of the model repeating the same lines verbatim.\n\n* `presence_penalty` number min -2 max 2\n\nIncreases the likelihood of the model introducing new topics.\n\n* `messages` array required\n\nAn array of message objects representing the conversation history.\n\n* `role` string required\n\nThe role of the message sender (e.g., 'user', 'assistant', 'system', 'tool').\n\n* `content` string required\n\nThe content of the message as a string.\n\n* `name` string required\n\n* `code` string required\n\nA list of tools available for the assistant to use.\n\n* `name` string required\n\nThe name of the tool. More descriptive the better.\n\n* `description` string required\n\nA brief description of what the tool does.\n\n* `parameters` object required\n\nSchema defining the parameters accepted by the tool.\n\n* `type` string required\n\nThe type of the parameters object (usually 'object').\n\nList of required parameter names.\n\n* `properties` object required\n\nDefinitions of each parameter.\n\n* `additionalProperties` object\n\n* `type` string required\n\nThe data type of the parameter.\n\n* `description` string required\n\nA description of the expected parameter.\n\n* `type` string required\n\nSpecifies the type of tool (e.g., 'function').\n\n* `function` object required\n\nDetails of the function tool.\n\n* `name` string required\n\nThe name of the function.\n\n* `description` string required\n\nA brief description of what the function does.\n\n* `parameters` object required\n\nSchema defining the parameters accepted by the function.\n\n* `type` string required\n\nThe type of the parameters object (usually 'object').\n\nList of required parameter names.\n\n* `properties` object required\n\nDefinitions of each parameter.\n\n* `additionalProperties` object\n\n* `type` string required\n\nThe data type of the parameter.\n\n* `description` string required\n\nA description of the expected parameter.\n\n* `response_format` object\n\nIf true, a chat template is not applied and you must adhere to the specific model's expected formatting.\n\nIf true, the response will be streamed back incrementally using SSE, Server Sent Events.\n\n* `max_tokens` integer default 2000\n\nThe maximum number of tokens to generate in the response.\n\n* `temperature` number default 0.6 min 0 max 5\n\nControls the randomness of the output; higher values produce more random results.\n\n* `top_p` number min 0.001 max 1\n\nAdjusts the creativity of the AI's responses by controlling how many possible words it considers. Lower values make outputs more predictable; higher values allow for more varied and creative responses.\n\n* `top_k` integer min 1 max 50\n\nLimits the AI to choose from the top 'k' most probable words. Lower values make responses more focused; higher values introduce more variety and potential surprises.\n\n* `seed` integer min 1 max 9999999999\n\nRandom seed for reproducibility of the generation.\n\n* `repetition_penalty` number min 0 max 2\n\nPenalty for repeated tokens; higher values discourage repetition.\n\n* `frequency_penalty` number min -2 max 2\n\nDecreases the likelihood of the model repeating the same lines verbatim.\n\n* `presence_penalty` number min -2 max 2\n\nIncreases the likelihood of the model introducing new topics.\n\n* `requests` array required\n\n* `prompt` string required min 1\n\nThe input text prompt for the model to generate a response.\n\nName of the LoRA (Low-Rank Adaptation) model to fine-tune the base model.\n\n* `response_format` object\n\nIf true, a chat template is not applied and you must adhere to the specific model's expected formatting.\n\nIf true, the response will be streamed back incrementally using SSE, Server Sent Events.\n\n* `max_tokens` integer default 256\n\nThe maximum number of tokens to generate in the response.\n\n* `temperature` number default 0.6 min 0 max 5\n\nControls the randomness of the output; higher values produce more random results.\n\n* `top_p` number min 0.001 max 1\n\nAdjusts the creativity of the AI's responses by controlling how many possible words it considers. Lower values make outputs more predictable; higher values allow for more varied and creative responses.\n\n* `top_k` integer min 1 max 50\n\nLimits the AI to choose from the top 'k' most probable words. Lower values make responses more focused; higher values introduce more variety and potential surprises.\n\n* `seed` integer min 1 max 9999999999\n\nRandom seed for reproducibility of the generation.\n\n* `repetition_penalty` number min 0 max 2\n\nPenalty for repeated tokens; higher values discourage repetition.\n\n* `frequency_penalty` number min -2 max 2\n\nDecreases the likelihood of the model repeating the same lines verbatim.\n\n* `presence_penalty` number min -2 max 2\n\nIncreases the likelihood of the model introducing new topics.\n\n* `messages` array required\n\nAn array of message objects representing the conversation history.\n\n* `role` string required\n\nThe role of the message sender (e.g., 'user', 'assistant', 'system', 'tool').\n\n* `content` string required\n\nThe content of the message as a string.\n\n* `name` string required\n\n* `code` string required\n\nA list of tools available for the assistant to use.\n\n* `name` string required\n\nThe name of the tool. More descriptive the better.\n\n* `description` string required\n\nA brief description of what the tool does.\n\n* `parameters` object required\n\nSchema defining the parameters accepted by the tool.\n\n* `type` string required\n\nThe type of the parameters object (usually 'object').\n\nList of required parameter names.\n\n* `properties` object required\n\nDefinitions of each parameter.\n\n* `additionalProperties` object\n\n* `type` string required\n\nThe data type of the parameter.\n\n* `description` string required\n\nA description of the expected parameter.\n\n* `type` string required\n\nSpecifies the type of tool (e.g., 'function').\n\n* `function` object required\n\nDetails of the function tool.\n\n* `name` string required\n\nThe name of the function.\n\n* `description` string required\n\nA brief description of what the function does.\n\n* `parameters` object required\n\nSchema defining the parameters accepted by the function.\n\n* `type` string required\n\nThe type of the parameters object (usually 'object').\n\nList of required parameter names.\n\n* `properties` object required\n\nDefinitions of each parameter.\n\n* `additionalProperties` object\n\n* `type` string required\n\nThe data type of the parameter.\n\n* `description` string required\n\nA description of the expected parameter.\n\n* `response_format` object\n\nIf true, a chat template is not applied and you must adhere to the specific model's expected formatting.\n\nIf true, the response will be streamed back incrementally using SSE, Server Sent Events.\n\n* `max_tokens` integer default 256\n\nThe maximum number of tokens to generate in the response.\n\n* `temperature` number default 0.6 min 0 max 5\n\nControls the randomness of the output; higher values produce more random results.\n\n* `top_p` number min 0.001 max 1\n\nAdjusts the creativity of the AI's responses by controlling how many possible words it considers. Lower values make outputs more predictable; higher values allow for more varied and creative responses.\n\n* `top_k` integer min 1 max 50\n\nLimits the AI to choose from the top 'k' most probable words. Lower values make responses more focused; higher values introduce more variety and potential surprises.\n\n* `seed` integer min 1 max 9999999999\n\nRandom seed for reproducibility of the generation.\n\n* `repetition_penalty` number min 0 max 2\n\nPenalty for repeated tokens; higher values discourage repetition.\n\n* `frequency_penalty` number min -2 max 2\n\nDecreases the likelihood of the model repeating the same lines verbatim.\n\n* `presence_penalty` number min -2 max 2\n\nIncreases the likelihood of the model introducing new topics.\n\nUnique identifier for the completion\n\nObject type identifier\n\nUnix timestamp of when the completion was created\n\nModel used for the completion\n\nList of completion choices\n\nIndex of the choice in the list\n\nThe message generated by the model\n\n* `role` string required\n\nRole of the message author\n\n* `content` string required\n\nThe content of the message\n\n* `reasoning_content` string\n\nInternal reasoning content (if available)\n\nTool calls made by the assistant\n\n* `id` string required\n\nUnique identifier for the tool call\n\n* `type` string required\n\n* `function` object required\n\n* `name` string required\n\nName of the function to call\n\n* `arguments` string required\n\nJSON string of arguments for the function\n\n* `finish_reason` string\n\nReason why the model stopped generating\n\n* `stop_reason` string\n\nStop reason (may be null)\n\nLog probabilities (if requested)\n\nUsage statistics for the inference request\n\n* `prompt_tokens` number 0\n\nTotal number of tokens in input\n\n* `completion_tokens` number 0\n\nTotal number of tokens in output\n\n* `total_tokens` number 0\n\nTotal number of input and output tokens\n\n* `prompt_logprobs` object\n\nLog probabilities for the prompt (if requested)\n\nUnique identifier for the completion\n\nObject type identifier\n\nUnix timestamp of when the completion was created\n\nModel used for the completion\n\nList of completion choices\n\n* `index` number required\n\nIndex of the choice in the list\n\n* `text` string required\n\nThe generated text completion\n\n* `finish_reason` string required\n\nReason why the model stopped generating\n\n* `stop_reason` string\n\nStop reason (may be null)\n\nLog probabilities (if requested)\n\n* `prompt_logprobs` object\n\nLog probabilities for the prompt (if requested)\n\nUsage statistics for the inference request\n\n* `prompt_tokens` number 0\n\nTotal number of tokens in input\n\n* `completion_tokens` number 0\n\nTotal number of tokens in output\n\n* `total_tokens` number 0\n\nTotal number of input and output tokens\n\n* `request_id` string\n\nThe async request id that can be used to obtain the results.\n\nThe following schemas are based on JSON Schema\n\n<page>\n---\ntitle: gpt-oss-120b · Cloudflare Workers AI docs\ndescription: OpenAI’s open-weight models designed for powerful reasoning,\n  agentic tasks, and versatile developer use cases – gpt-oss-120b is for\n  production, general purpose, high reasoning use-cases.\nchatbotDeprioritize: false\nsource_url:\n  html: https://developers.cloudflare.com/workers-ai/models/gpt-oss-120b/\n  md: https://developers.cloudflare.com/workers-ai/models/gpt-oss-120b/index.md\n---\n\n![OpenAI logo](https://developers.cloudflare.com/_astro/openai.ChTKThcR.svg)",
  "code_samples": [
    {
      "code": "export interface Env {\n  AI: Ai;\n}\n\n\nexport default {\n  async fetch(request, env): Promise<Response> {\n\n\n    const messages = [\n      { role: \"system\", content: \"You are a friendly assistant\" },\n      {\n        role: \"user\",\n        content: \"What is the origin of the phrase Hello, World\",\n      },\n    ];\n\n\n    const stream = await env.AI.run(\"@cf/aisingapore/gemma-sea-lion-v4-27b-it\", {\n      messages,\n      stream: true,\n    });\n\n\n    return new Response(stream, {\n      headers: { \"content-type\": \"text/event-stream\" },\n    });\n  },\n} satisfies ExportedHandler<Env>;",
      "language": "ts"
    },
    {
      "code": "export interface Env {\n  AI: Ai;\n}\n\n\nexport default {\n  async fetch(request, env): Promise<Response> {\n\n\n    const messages = [\n      { role: \"system\", content: \"You are a friendly assistant\" },\n      {\n        role: \"user\",\n        content: \"What is the origin of the phrase Hello, World\",\n      },\n    ];\n    const response = await env.AI.run(\"@cf/aisingapore/gemma-sea-lion-v4-27b-it\", { messages });\n\n\n    return Response.json(response);\n  },\n} satisfies ExportedHandler<Env>;",
      "language": "ts"
    },
    {
      "code": "import os\nimport requests\n\n\nACCOUNT_ID = \"your-account-id\"\nAUTH_TOKEN = os.environ.get(\"CLOUDFLARE_AUTH_TOKEN\")\n\n\nprompt = \"Tell me all about PEP-8\"\nresponse = requests.post(\n  f\"https://api.cloudflare.com/client/v4/accounts/{ACCOUNT_ID}/ai/run/@cf/aisingapore/gemma-sea-lion-v4-27b-it\",\n    headers={\"Authorization\": f\"Bearer {AUTH_TOKEN}\"},\n    json={\n      \"messages\": [\n        {\"role\": \"system\", \"content\": \"You are a friendly assistant\"},\n        {\"role\": \"user\", \"content\": prompt}\n      ]\n    }\n)\nresult = response.json()\nprint(result)",
      "language": "py"
    },
    {
      "code": "curl https://api.cloudflare.com/client/v4/accounts/$CLOUDFLARE_ACCOUNT_ID/ai/run/@cf/aisingapore/gemma-sea-lion-v4-27b-it \\\n  -X POST \\\n  -H \"Authorization: Bearer $CLOUDFLARE_AUTH_TOKEN\" \\\n  -d '{ \"messages\": [{ \"role\": \"system\", \"content\": \"You are a friendly assistant\" }, { \"role\": \"user\", \"content\": \"Why is pizza so good\" }]}'",
      "language": "sh"
    },
    {
      "code": "{\n      \"type\": \"object\",\n      \"oneOf\": [\n          {\n              \"title\": \"Prompt\",\n              \"properties\": {\n                  \"prompt\": {\n                      \"type\": \"string\",\n                      \"minLength\": 1,\n                      \"description\": \"The input text prompt for the model to generate a response.\"\n                  },\n                  \"lora\": {\n                      \"type\": \"string\",\n                      \"description\": \"Name of the LoRA (Low-Rank Adaptation) model to fine-tune the base model.\"\n                  },\n                  \"response_format\": {\n                      \"title\": \"JSON Mode\",\n                      \"type\": \"object\",\n                      \"properties\": {\n                          \"type\": {\n                              \"type\": \"string\",\n                              \"enum\": [\n                                  \"json_object\",\n                                  \"json_schema\"\n                              ]\n                          },\n                          \"json_schema\": {}\n                      }\n                  },\n                  \"raw\": {\n                      \"type\": \"boolean\",\n                      \"default\": false,\n                      \"description\": \"If true, a chat template is not applied and you must adhere to the specific model's expected formatting.\"\n                  },\n                  \"stream\": {\n                      \"type\": \"boolean\",\n                      \"default\": false,\n                      \"description\": \"If true, the response will be streamed back incrementally using SSE, Server Sent Events.\"\n                  },\n                  \"max_tokens\": {\n                      \"type\": \"integer\",\n                      \"default\": 2000,\n                      \"description\": \"The maximum number of tokens to generate in the response.\"\n                  },\n                  \"temperature\": {\n                      \"type\": \"number\",\n                      \"default\": 0.6,\n                      \"minimum\": 0,\n                      \"maximum\": 5,\n                      \"description\": \"Controls the randomness of the output; higher values produce more random results.\"\n                  },\n                  \"top_p\": {\n                      \"type\": \"number\",\n                      \"minimum\": 0.001,\n                      \"maximum\": 1,\n                      \"description\": \"Adjusts the creativity of the AI's responses by controlling how many possible words it considers. Lower values make outputs more predictable; higher values allow for more varied and creative responses.\"\n                  },\n                  \"top_k\": {\n                      \"type\": \"integer\",\n                      \"minimum\": 1,\n                      \"maximum\": 50,\n                      \"description\": \"Limits the AI to choose from the top 'k' most probable words. Lower values make responses more focused; higher values introduce more variety and potential surprises.\"\n                  },\n                  \"seed\": {\n                      \"type\": \"integer\",\n                      \"minimum\": 1,\n                      \"maximum\": 9999999999,\n                      \"description\": \"Random seed for reproducibility of the generation.\"\n                  },\n                  \"repetition_penalty\": {\n                      \"type\": \"number\",\n                      \"minimum\": 0,\n                      \"maximum\": 2,\n                      \"description\": \"Penalty for repeated tokens; higher values discourage repetition.\"\n                  },\n                  \"frequency_penalty\": {\n                      \"type\": \"number\",\n                      \"minimum\": -2,\n                      \"maximum\": 2,\n                      \"description\": \"Decreases the likelihood of the model repeating the same lines verbatim.\"\n                  },\n                  \"presence_penalty\": {\n                      \"type\": \"number\",\n                      \"minimum\": -2,\n                      \"maximum\": 2,\n                      \"description\": \"Increases the likelihood of the model introducing new topics.\"\n                  }\n              },\n              \"required\": [\n                  \"prompt\"\n              ]\n          },\n          {\n              \"title\": \"Messages\",\n              \"properties\": {\n                  \"messages\": {\n                      \"type\": \"array\",\n                      \"description\": \"An array of message objects representing the conversation history.\",\n                      \"items\": {\n                          \"type\": \"object\",\n                          \"properties\": {\n                              \"role\": {\n                                  \"type\": \"string\",\n                                  \"description\": \"The role of the message sender (e.g., 'user', 'assistant', 'system', 'tool').\"\n                              },\n                              \"content\": {\n                                  \"type\": \"string\",\n                                  \"description\": \"The content of the message as a string.\"\n                              }\n                          },\n                          \"required\": [\n                              \"role\",\n                              \"content\"\n                          ]\n                      }\n                  },\n                  \"functions\": {\n                      \"type\": \"array\",\n                      \"items\": {\n                          \"type\": \"object\",\n                          \"properties\": {\n                              \"name\": {\n                                  \"type\": \"string\"\n                              },\n                              \"code\": {\n                                  \"type\": \"string\"\n                              }\n                          },\n                          \"required\": [\n                              \"name\",\n                              \"code\"\n                          ]\n                      }\n                  },\n                  \"tools\": {\n                      \"type\": \"array\",\n                      \"description\": \"A list of tools available for the assistant to use.\",\n                      \"items\": {\n                          \"type\": \"object\",\n                          \"oneOf\": [\n                              {\n                                  \"properties\": {\n                                      \"name\": {\n                                          \"type\": \"string\",\n                                          \"description\": \"The name of the tool. More descriptive the better.\"\n                                      },\n                                      \"description\": {\n                                          \"type\": \"string\",\n                                          \"description\": \"A brief description of what the tool does.\"\n                                      },\n                                      \"parameters\": {\n                                          \"type\": \"object\",\n                                          \"description\": \"Schema defining the parameters accepted by the tool.\",\n                                          \"properties\": {\n                                              \"type\": {\n                                                  \"type\": \"string\",\n                                                  \"description\": \"The type of the parameters object (usually 'object').\"\n                                              },\n                                              \"required\": {\n                                                  \"type\": \"array\",\n                                                  \"description\": \"List of required parameter names.\",\n                                                  \"items\": {\n                                                      \"type\": \"string\"\n                                                  }\n                                              },\n                                              \"properties\": {\n                                                  \"type\": \"object\",\n                                                  \"description\": \"Definitions of each parameter.\",\n                                                  \"additionalProperties\": {\n                                                      \"type\": \"object\",\n                                                      \"properties\": {\n                                                          \"type\": {\n                                                              \"type\": \"string\",\n                                                              \"description\": \"The data type of the parameter.\"\n                                                          },\n                                                          \"description\": {\n                                                              \"type\": \"string\",\n                                                              \"description\": \"A description of the expected parameter.\"\n                                                          }\n                                                      },\n                                                      \"required\": [\n                                                          \"type\",\n                                                          \"description\"\n                                                      ]\n                                                  }\n                                              }\n                                          },\n                                          \"required\": [\n                                              \"type\",\n                                              \"properties\"\n                                          ]\n                                      }\n                                  },\n                                  \"required\": [\n                                      \"name\",\n                                      \"description\",\n                                      \"parameters\"\n                                  ]\n                              },\n                              {\n                                  \"properties\": {\n                                      \"type\": {\n                                          \"type\": \"string\",\n                                          \"description\": \"Specifies the type of tool (e.g., 'function').\"\n                                      },\n                                      \"function\": {\n                                          \"type\": \"object\",\n                                          \"description\": \"Details of the function tool.\",\n                                          \"properties\": {\n                                              \"name\": {\n                                                  \"type\": \"string\",\n                                                  \"description\": \"The name of the function.\"\n                                              },\n                                              \"description\": {\n                                                  \"type\": \"string\",\n                                                  \"description\": \"A brief description of what the function does.\"\n                                              },\n                                              \"parameters\": {\n                                                  \"type\": \"object\",\n                                                  \"description\": \"Schema defining the parameters accepted by the function.\",\n                                                  \"properties\": {\n                                                      \"type\": {\n                                                          \"type\": \"string\",\n                                                          \"description\": \"The type of the parameters object (usually 'object').\"\n                                                      },\n                                                      \"required\": {\n                                                          \"type\": \"array\",\n                                                          \"description\": \"List of required parameter names.\",\n                                                          \"items\": {\n                                                              \"type\": \"string\"\n                                                          }\n                                                      },\n                                                      \"properties\": {\n                                                          \"type\": \"object\",\n                                                          \"description\": \"Definitions of each parameter.\",\n                                                          \"additionalProperties\": {\n                                                              \"type\": \"object\",\n                                                              \"properties\": {\n                                                                  \"type\": {\n                                                                      \"type\": \"string\",\n                                                                      \"description\": \"The data type of the parameter.\"\n                                                                  },\n                                                                  \"description\": {\n                                                                      \"type\": \"string\",\n                                                                      \"description\": \"A description of the expected parameter.\"\n                                                                  }\n                                                              },\n                                                              \"required\": [\n                                                                  \"type\",\n                                                                  \"description\"\n                                                              ]\n                                                          }\n                                                      }\n                                                  },\n                                                  \"required\": [\n                                                      \"type\",\n                                                      \"properties\"\n                                                  ]\n                                              }\n                                          },\n                                          \"required\": [\n                                              \"name\",\n                                              \"description\",\n                                              \"parameters\"\n                                          ]\n                                      }\n                                  },\n                                  \"required\": [\n                                      \"type\",\n                                      \"function\"\n                                  ]\n                              }\n                          ]\n                      }\n                  },\n                  \"response_format\": {\n                      \"title\": \"JSON Mode\",\n                      \"type\": \"object\",\n                      \"properties\": {\n                          \"type\": {\n                              \"type\": \"string\",\n                              \"enum\": [\n                                  \"json_object\",\n                                  \"json_schema\"\n                              ]\n                          },\n                          \"json_schema\": {}\n                      }\n                  },\n                  \"raw\": {\n                      \"type\": \"boolean\",\n                      \"default\": false,\n                      \"description\": \"If true, a chat template is not applied and you must adhere to the specific model's expected formatting.\"\n                  },\n                  \"stream\": {\n                      \"type\": \"boolean\",\n                      \"default\": false,\n                      \"description\": \"If true, the response will be streamed back incrementally using SSE, Server Sent Events.\"\n                  },\n                  \"max_tokens\": {\n                      \"type\": \"integer\",\n                      \"default\": 2000,\n                      \"description\": \"The maximum number of tokens to generate in the response.\"\n                  },\n                  \"temperature\": {\n                      \"type\": \"number\",\n                      \"default\": 0.6,\n                      \"minimum\": 0,\n                      \"maximum\": 5,\n                      \"description\": \"Controls the randomness of the output; higher values produce more random results.\"\n                  },\n                  \"top_p\": {\n                      \"type\": \"number\",\n                      \"minimum\": 0.001,\n                      \"maximum\": 1,\n                      \"description\": \"Adjusts the creativity of the AI's responses by controlling how many possible words it considers. Lower values make outputs more predictable; higher values allow for more varied and creative responses.\"\n                  },\n                  \"top_k\": {\n                      \"type\": \"integer\",\n                      \"minimum\": 1,\n                      \"maximum\": 50,\n                      \"description\": \"Limits the AI to choose from the top 'k' most probable words. Lower values make responses more focused; higher values introduce more variety and potential surprises.\"\n                  },\n                  \"seed\": {\n                      \"type\": \"integer\",\n                      \"minimum\": 1,\n                      \"maximum\": 9999999999,\n                      \"description\": \"Random seed for reproducibility of the generation.\"\n                  },\n                  \"repetition_penalty\": {\n                      \"type\": \"number\",\n                      \"minimum\": 0,\n                      \"maximum\": 2,\n                      \"description\": \"Penalty for repeated tokens; higher values discourage repetition.\"\n                  },\n                  \"frequency_penalty\": {\n                      \"type\": \"number\",\n                      \"minimum\": -2,\n                      \"maximum\": 2,\n                      \"description\": \"Decreases the likelihood of the model repeating the same lines verbatim.\"\n                  },\n                  \"presence_penalty\": {\n                      \"type\": \"number\",\n                      \"minimum\": -2,\n                      \"maximum\": 2,\n                      \"description\": \"Increases the likelihood of the model introducing new topics.\"\n                  }\n              },\n              \"required\": [\n                  \"messages\"\n              ]\n          },\n          {\n              \"title\": \"Async Batch\",\n              \"type\": \"object\",\n              \"properties\": {\n                  \"requests\": {\n                      \"type\": \"array\",\n                      \"items\": {\n                          \"type\": \"object\",\n                          \"oneOf\": [\n                              {\n                                  \"title\": \"Prompt\",\n                                  \"properties\": {\n                                      \"prompt\": {\n                                          \"type\": \"string\",\n                                          \"minLength\": 1,\n                                          \"description\": \"The input text prompt for the model to generate a response.\"\n                                      },\n                                      \"lora\": {\n                                          \"type\": \"string\",\n                                          \"description\": \"Name of the LoRA (Low-Rank Adaptation) model to fine-tune the base model.\"\n                                      },\n                                      \"response_format\": {\n                                          \"title\": \"JSON Mode\",\n                                          \"type\": \"object\",\n                                          \"properties\": {\n                                              \"type\": {\n                                                  \"type\": \"string\",\n                                                  \"enum\": [\n                                                      \"json_object\",\n                                                      \"json_schema\"\n                                                  ]\n                                              },\n                                              \"json_schema\": {}\n                                          }\n                                      },\n                                      \"raw\": {\n                                          \"type\": \"boolean\",\n                                          \"default\": false,\n                                          \"description\": \"If true, a chat template is not applied and you must adhere to the specific model's expected formatting.\"\n                                      },\n                                      \"stream\": {\n                                          \"type\": \"boolean\",\n                                          \"default\": false,\n                                          \"description\": \"If true, the response will be streamed back incrementally using SSE, Server Sent Events.\"\n                                      },\n                                      \"max_tokens\": {\n                                          \"type\": \"integer\",\n                                          \"default\": 256,\n                                          \"description\": \"The maximum number of tokens to generate in the response.\"\n                                      },\n                                      \"temperature\": {\n                                          \"type\": \"number\",\n                                          \"default\": 0.6,\n                                          \"minimum\": 0,\n                                          \"maximum\": 5,\n                                          \"description\": \"Controls the randomness of the output; higher values produce more random results.\"\n                                      },\n                                      \"top_p\": {\n                                          \"type\": \"number\",\n                                          \"minimum\": 0.001,\n                                          \"maximum\": 1,\n                                          \"description\": \"Adjusts the creativity of the AI's responses by controlling how many possible words it considers. Lower values make outputs more predictable; higher values allow for more varied and creative responses.\"\n                                      },\n                                      \"top_k\": {\n                                          \"type\": \"integer\",\n                                          \"minimum\": 1,\n                                          \"maximum\": 50,\n                                          \"description\": \"Limits the AI to choose from the top 'k' most probable words. Lower values make responses more focused; higher values introduce more variety and potential surprises.\"\n                                      },\n                                      \"seed\": {\n                                          \"type\": \"integer\",\n                                          \"minimum\": 1,\n                                          \"maximum\": 9999999999,\n                                          \"description\": \"Random seed for reproducibility of the generation.\"\n                                      },\n                                      \"repetition_penalty\": {\n                                          \"type\": \"number\",\n                                          \"minimum\": 0,\n                                          \"maximum\": 2,\n                                          \"description\": \"Penalty for repeated tokens; higher values discourage repetition.\"\n                                      },\n                                      \"frequency_penalty\": {\n                                          \"type\": \"number\",\n                                          \"minimum\": -2,\n                                          \"maximum\": 2,\n                                          \"description\": \"Decreases the likelihood of the model repeating the same lines verbatim.\"\n                                      },\n                                      \"presence_penalty\": {\n                                          \"type\": \"number\",\n                                          \"minimum\": -2,\n                                          \"maximum\": 2,\n                                          \"description\": \"Increases the likelihood of the model introducing new topics.\"\n                                      }\n                                  },\n                                  \"required\": [\n                                      \"prompt\"\n                                  ]\n                              },\n                              {\n                                  \"title\": \"Messages\",\n                                  \"properties\": {\n                                      \"messages\": {\n                                          \"type\": \"array\",\n                                          \"description\": \"An array of message objects representing the conversation history.\",\n                                          \"items\": {\n                                              \"type\": \"object\",\n                                              \"properties\": {\n                                                  \"role\": {\n                                                      \"type\": \"string\",\n                                                      \"description\": \"The role of the message sender (e.g., 'user', 'assistant', 'system', 'tool').\"\n                                                  },\n                                                  \"content\": {\n                                                      \"type\": \"string\",\n                                                      \"description\": \"The content of the message as a string.\"\n                                                  }\n                                              },\n                                              \"required\": [\n                                                  \"role\",\n                                                  \"content\"\n                                              ]\n                                          }\n                                      },\n                                      \"functions\": {\n                                          \"type\": \"array\",\n                                          \"items\": {\n                                              \"type\": \"object\",\n                                              \"properties\": {\n                                                  \"name\": {\n                                                      \"type\": \"string\"\n                                                  },\n                                                  \"code\": {\n                                                      \"type\": \"string\"\n                                                  }\n                                              },\n                                              \"required\": [\n                                                  \"name\",\n                                                  \"code\"\n                                              ]\n                                          }\n                                      },\n                                      \"tools\": {\n                                          \"type\": \"array\",\n                                          \"description\": \"A list of tools available for the assistant to use.\",\n                                          \"items\": {\n                                              \"type\": \"object\",\n                                              \"oneOf\": [\n                                                  {\n                                                      \"properties\": {\n                                                          \"name\": {\n                                                              \"type\": \"string\",\n                                                              \"description\": \"The name of the tool. More descriptive the better.\"\n                                                          },\n                                                          \"description\": {\n                                                              \"type\": \"string\",\n                                                              \"description\": \"A brief description of what the tool does.\"\n                                                          },\n                                                          \"parameters\": {\n                                                              \"type\": \"object\",\n                                                              \"description\": \"Schema defining the parameters accepted by the tool.\",\n                                                              \"properties\": {\n                                                                  \"type\": {\n                                                                      \"type\": \"string\",\n                                                                      \"description\": \"The type of the parameters object (usually 'object').\"\n                                                                  },\n                                                                  \"required\": {\n                                                                      \"type\": \"array\",\n                                                                      \"description\": \"List of required parameter names.\",\n                                                                      \"items\": {\n                                                                          \"type\": \"string\"\n                                                                      }\n                                                                  },\n                                                                  \"properties\": {\n                                                                      \"type\": \"object\",\n                                                                      \"description\": \"Definitions of each parameter.\",\n                                                                      \"additionalProperties\": {\n                                                                          \"type\": \"object\",\n                                                                          \"properties\": {\n                                                                              \"type\": {\n                                                                                  \"type\": \"string\",\n                                                                                  \"description\": \"The data type of the parameter.\"\n                                                                              },\n                                                                              \"description\": {\n                                                                                  \"type\": \"string\",\n                                                                                  \"description\": \"A description of the expected parameter.\"\n                                                                              }\n                                                                          },\n                                                                          \"required\": [\n                                                                              \"type\",\n                                                                              \"description\"\n                                                                          ]\n                                                                      }\n                                                                  }\n                                                              },\n                                                              \"required\": [\n                                                                  \"type\",\n                                                                  \"properties\"\n                                                              ]\n                                                          }\n                                                      },\n                                                      \"required\": [\n                                                          \"name\",\n                                                          \"description\",\n                                                          \"parameters\"\n                                                      ]\n                                                  },\n                                                  {\n                                                      \"properties\": {\n                                                          \"type\": {\n                                                              \"type\": \"string\",\n                                                              \"description\": \"Specifies the type of tool (e.g., 'function').\"\n                                                          },\n                                                          \"function\": {\n                                                              \"type\": \"object\",\n                                                              \"description\": \"Details of the function tool.\",\n                                                              \"properties\": {\n                                                                  \"name\": {\n                                                                      \"type\": \"string\",\n                                                                      \"description\": \"The name of the function.\"\n                                                                  },\n                                                                  \"description\": {\n                                                                      \"type\": \"string\",\n                                                                      \"description\": \"A brief description of what the function does.\"\n                                                                  },\n                                                                  \"parameters\": {\n                                                                      \"type\": \"object\",\n                                                                      \"description\": \"Schema defining the parameters accepted by the function.\",\n                                                                      \"properties\": {\n                                                                          \"type\": {\n                                                                              \"type\": \"string\",\n                                                                              \"description\": \"The type of the parameters object (usually 'object').\"\n                                                                          },\n                                                                          \"required\": {\n                                                                              \"type\": \"array\",\n                                                                              \"description\": \"List of required parameter names.\",\n                                                                              \"items\": {\n                                                                                  \"type\": \"string\"\n                                                                              }\n                                                                          },\n                                                                          \"properties\": {\n                                                                              \"type\": \"object\",\n                                                                              \"description\": \"Definitions of each parameter.\",\n                                                                              \"additionalProperties\": {\n                                                                                  \"type\": \"object\",\n                                                                                  \"properties\": {\n                                                                                      \"type\": {\n                                                                                          \"type\": \"string\",\n                                                                                          \"description\": \"The data type of the parameter.\"\n                                                                                      },\n                                                                                      \"description\": {\n                                                                                          \"type\": \"string\",\n                                                                                          \"description\": \"A description of the expected parameter.\"\n                                                                                      }\n                                                                                  },\n                                                                                  \"required\": [\n                                                                                      \"type\",\n                                                                                      \"description\"\n                                                                                  ]\n                                                                              }\n                                                                          }\n                                                                      },\n                                                                      \"required\": [\n                                                                          \"type\",\n                                                                          \"properties\"\n                                                                      ]\n                                                                  }\n                                                              },\n                                                              \"required\": [\n                                                                  \"name\",\n                                                                  \"description\",\n                                                                  \"parameters\"\n                                                              ]\n                                                          }\n                                                      },\n                                                      \"required\": [\n                                                          \"type\",\n                                                          \"function\"\n                                                      ]\n                                                  }\n                                              ]\n                                          }\n                                      },\n                                      \"response_format\": {\n                                          \"title\": \"JSON Mode\",\n                                          \"type\": \"object\",\n                                          \"properties\": {\n                                              \"type\": {\n                                                  \"type\": \"string\",\n                                                  \"enum\": [\n                                                      \"json_object\",\n                                                      \"json_schema\"\n                                                  ]\n                                              },\n                                              \"json_schema\": {}\n                                          }\n                                      },\n                                      \"raw\": {\n                                          \"type\": \"boolean\",\n                                          \"default\": false,\n                                          \"description\": \"If true, a chat template is not applied and you must adhere to the specific model's expected formatting.\"\n                                      },\n                                      \"stream\": {\n                                          \"type\": \"boolean\",\n                                          \"default\": false,\n                                          \"description\": \"If true, the response will be streamed back incrementally using SSE, Server Sent Events.\"\n                                      },\n                                      \"max_tokens\": {\n                                          \"type\": \"integer\",\n                                          \"default\": 256,\n                                          \"description\": \"The maximum number of tokens to generate in the response.\"\n                                      },\n                                      \"temperature\": {\n                                          \"type\": \"number\",\n                                          \"default\": 0.6,\n                                          \"minimum\": 0,\n                                          \"maximum\": 5,\n                                          \"description\": \"Controls the randomness of the output; higher values produce more random results.\"\n                                      },\n                                      \"top_p\": {\n                                          \"type\": \"number\",\n                                          \"minimum\": 0.001,\n                                          \"maximum\": 1,\n                                          \"description\": \"Adjusts the creativity of the AI's responses by controlling how many possible words it considers. Lower values make outputs more predictable; higher values allow for more varied and creative responses.\"\n                                      },\n                                      \"top_k\": {\n                                          \"type\": \"integer\",\n                                          \"minimum\": 1,\n                                          \"maximum\": 50,\n                                          \"description\": \"Limits the AI to choose from the top 'k' most probable words. Lower values make responses more focused; higher values introduce more variety and potential surprises.\"\n                                      },\n                                      \"seed\": {\n                                          \"type\": \"integer\",\n                                          \"minimum\": 1,\n                                          \"maximum\": 9999999999,\n                                          \"description\": \"Random seed for reproducibility of the generation.\"\n                                      },\n                                      \"repetition_penalty\": {\n                                          \"type\": \"number\",\n                                          \"minimum\": 0,\n                                          \"maximum\": 2,\n                                          \"description\": \"Penalty for repeated tokens; higher values discourage repetition.\"\n                                      },\n                                      \"frequency_penalty\": {\n                                          \"type\": \"number\",\n                                          \"minimum\": -2,\n                                          \"maximum\": 2,\n                                          \"description\": \"Decreases the likelihood of the model repeating the same lines verbatim.\"\n                                      },\n                                      \"presence_penalty\": {\n                                          \"type\": \"number\",\n                                          \"minimum\": -2,\n                                          \"maximum\": 2,\n                                          \"description\": \"Increases the likelihood of the model introducing new topics.\"\n                                      }\n                                  },\n                                  \"required\": [\n                                      \"messages\"\n                                  ]\n                              }\n                          ]\n                      }\n                  }\n              },\n              \"required\": [\n                  \"requests\"\n              ]\n          }\n      ]\n  }",
      "language": "json"
    },
    {
      "code": "{\n      \"oneOf\": [\n          {\n              \"type\": \"object\",\n              \"contentType\": \"application/json\",\n              \"title\": \"Chat Completion Response\",\n              \"properties\": {\n                  \"id\": {\n                      \"type\": \"string\",\n                      \"description\": \"Unique identifier for the completion\"\n                  },\n                  \"object\": {\n                      \"type\": \"string\",\n                      \"enum\": [\n                          \"chat.completion\"\n                      ],\n                      \"description\": \"Object type identifier\"\n                  },\n                  \"created\": {\n                      \"type\": \"number\",\n                      \"description\": \"Unix timestamp of when the completion was created\"\n                  },\n                  \"model\": {\n                      \"type\": \"string\",\n                      \"description\": \"Model used for the completion\"\n                  },\n                  \"choices\": {\n                      \"type\": \"array\",\n                      \"description\": \"List of completion choices\",\n                      \"items\": {\n                          \"type\": \"object\",\n                          \"properties\": {\n                              \"index\": {\n                                  \"type\": \"number\",\n                                  \"description\": \"Index of the choice in the list\"\n                              },\n                              \"message\": {\n                                  \"type\": \"object\",\n                                  \"description\": \"The message generated by the model\",\n                                  \"properties\": {\n                                      \"role\": {\n                                          \"type\": \"string\",\n                                          \"description\": \"Role of the message author\"\n                                      },\n                                      \"content\": {\n                                          \"type\": \"string\",\n                                          \"description\": \"The content of the message\"\n                                      },\n                                      \"reasoning_content\": {\n                                          \"type\": \"string\",\n                                          \"description\": \"Internal reasoning content (if available)\"\n                                      },\n                                      \"tool_calls\": {\n                                          \"type\": \"array\",\n                                          \"description\": \"Tool calls made by the assistant\",\n                                          \"items\": {\n                                              \"type\": \"object\",\n                                              \"properties\": {\n                                                  \"id\": {\n                                                      \"type\": \"string\",\n                                                      \"description\": \"Unique identifier for the tool call\"\n                                                  },\n                                                  \"type\": {\n                                                      \"type\": \"string\",\n                                                      \"enum\": [\n                                                          \"function\"\n                                                      ],\n                                                      \"description\": \"Type of tool call\"\n                                                  },\n                                                  \"function\": {\n                                                      \"type\": \"object\",\n                                                      \"properties\": {\n                                                          \"name\": {\n                                                              \"type\": \"string\",\n                                                              \"description\": \"Name of the function to call\"\n                                                          },\n                                                          \"arguments\": {\n                                                              \"type\": \"string\",\n                                                              \"description\": \"JSON string of arguments for the function\"\n                                                          }\n                                                      },\n                                                      \"required\": [\n                                                          \"name\",\n                                                          \"arguments\"\n                                                      ]\n                                                  }\n                                              },\n                                              \"required\": [\n                                                  \"id\",\n                                                  \"type\",\n                                                  \"function\"\n                                              ]\n                                          }\n                                      }\n                                  },\n                                  \"required\": [\n                                      \"role\",\n                                      \"content\"\n                                  ]\n                              },\n                              \"finish_reason\": {\n                                  \"type\": \"string\",\n                                  \"description\": \"Reason why the model stopped generating\"\n                              },\n                              \"stop_reason\": {\n                                  \"type\": [\n                                      \"string\",\n                                      \"null\"\n                                  ],\n                                  \"description\": \"Stop reason (may be null)\"\n                              },\n                              \"logprobs\": {\n                                  \"type\": [\n                                      \"object\",\n                                      \"null\"\n                                  ],\n                                  \"description\": \"Log probabilities (if requested)\"\n                              }\n                          }\n                      }\n                  },\n                  \"usage\": {\n                      \"type\": \"object\",\n                      \"description\": \"Usage statistics for the inference request\",\n                      \"properties\": {\n                          \"prompt_tokens\": {\n                              \"type\": \"number\",\n                              \"description\": \"Total number of tokens in input\",\n                              \"default\": 0\n                          },\n                          \"completion_tokens\": {\n                              \"type\": \"number\",\n                              \"description\": \"Total number of tokens in output\",\n                              \"default\": 0\n                          },\n                          \"total_tokens\": {\n                              \"type\": \"number\",\n                              \"description\": \"Total number of input and output tokens\",\n                              \"default\": 0\n                          }\n                      }\n                  },\n                  \"prompt_logprobs\": {\n                      \"type\": [\n                          \"object\",\n                          \"null\"\n                      ],\n                      \"description\": \"Log probabilities for the prompt (if requested)\"\n                  }\n              }\n          },\n          {\n              \"type\": \"object\",\n              \"contentType\": \"application/json\",\n              \"title\": \"Text Completion Response\",\n              \"properties\": {\n                  \"id\": {\n                      \"type\": \"string\",\n                      \"description\": \"Unique identifier for the completion\"\n                  },\n                  \"object\": {\n                      \"type\": \"string\",\n                      \"enum\": [\n                          \"text_completion\"\n                      ],\n                      \"description\": \"Object type identifier\"\n                  },\n                  \"created\": {\n                      \"type\": \"number\",\n                      \"description\": \"Unix timestamp of when the completion was created\"\n                  },\n                  \"model\": {\n                      \"type\": \"string\",\n                      \"description\": \"Model used for the completion\"\n                  },\n                  \"choices\": {\n                      \"type\": \"array\",\n                      \"description\": \"List of completion choices\",\n                      \"items\": {\n                          \"type\": \"object\",\n                          \"properties\": {\n                              \"index\": {\n                                  \"type\": \"number\",\n                                  \"description\": \"Index of the choice in the list\"\n                              },\n                              \"text\": {\n                                  \"type\": \"string\",\n                                  \"description\": \"The generated text completion\"\n                              },\n                              \"finish_reason\": {\n                                  \"type\": \"string\",\n                                  \"description\": \"Reason why the model stopped generating\"\n                              },\n                              \"stop_reason\": {\n                                  \"type\": [\n                                      \"string\",\n                                      \"null\"\n                                  ],\n                                  \"description\": \"Stop reason (may be null)\"\n                              },\n                              \"logprobs\": {\n                                  \"type\": [\n                                      \"object\",\n                                      \"null\"\n                                  ],\n                                  \"description\": \"Log probabilities (if requested)\"\n                              },\n                              \"prompt_logprobs\": {\n                                  \"type\": [\n                                      \"object\",\n                                      \"null\"\n                                  ],\n                                  \"description\": \"Log probabilities for the prompt (if requested)\"\n                              }\n                          },\n                          \"required\": [\n                              \"index\",\n                              \"text\",\n                              \"finish_reason\"\n                          ]\n                      }\n                  },\n                  \"usage\": {\n                      \"type\": \"object\",\n                      \"description\": \"Usage statistics for the inference request\",\n                      \"properties\": {\n                          \"prompt_tokens\": {\n                              \"type\": \"number\",\n                              \"description\": \"Total number of tokens in input\",\n                              \"default\": 0\n                          },\n                          \"completion_tokens\": {\n                              \"type\": \"number\",\n                              \"description\": \"Total number of tokens in output\",\n                              \"default\": 0\n                          },\n                          \"total_tokens\": {\n                              \"type\": \"number\",\n                              \"description\": \"Total number of input and output tokens\",\n                              \"default\": 0\n                          }\n                      }\n                  }\n              }\n          },\n          {\n              \"type\": \"string\",\n              \"contentType\": \"text/event-stream\",\n              \"format\": \"binary\"\n          },\n          {\n              \"type\": \"object\",\n              \"contentType\": \"application/json\",\n              \"title\": \"Async response\",\n              \"properties\": {\n                  \"request_id\": {\n                      \"type\": \"string\",\n                      \"description\": \"The async request id that can be used to obtain the results.\"\n                  }\n              }\n          }\n      ]\n  }",
      "language": "json"
    }
  ],
  "headings": [
    {
      "level": "h2",
      "text": "Playground",
      "id": "playground"
    },
    {
      "level": "h2",
      "text": "Usage",
      "id": "usage"
    },
    {
      "level": "h2",
      "text": "Parameters",
      "id": "parameters"
    },
    {
      "level": "h3",
      "text": "Input",
      "id": "input"
    },
    {
      "level": "h3",
      "text": "Output",
      "id": "output"
    },
    {
      "level": "h2",
      "text": "API Schemas",
      "id": "api-schemas"
    }
  ],
  "url": "llms-txt#gemma-sea-lion-v4-27b-it",
  "links": []
}